cordra/__init__.py
cordra/auth.py
cordra/client.py
cordra/exceptions.py
cordra/models.py
cordra/py.typed
cordra_python-0.1.0.dist-info/licenses/LICENSE
cordra_python-0.1.0.dist-info/METADATA
cordra_python-0.1.0.dist-info/WHEEL
cordra_python-0.1.0.dist-info/top_level.txt
cordra_python-0.1.0.dist-info/RECORD
