Metadata-Version: 2.4
Name: cordra-python
Version: 0.1.0
Summary: Python client library for Cordra digital object repositories
Author: Royal Institute for Cultural Heritage (KIK-IRPA)
Maintainer: Royal Institute for Cultural Heritage (KIK-IRPA)
License: MIT
Project-URL: Homepage, https://github.com/kikirpa/cordra-python
Project-URL: Documentation, https://github.com/kikirpa/cordra-python#readme
Project-URL: Repository, https://github.com/kikirpa/cordra-python
Project-URL: Issues, https://github.com/kikirpa/cordra-python/issues
Project-URL: Changelog, https://github.com/kikirpa/cordra-python/blob/main/CHANGELOG.md
Keywords: cordra,digital-objects,repository,api-client,doip,rest-api
Classifier: Development Status :: 5 - Production/Stable
Classifier: Intended Audience :: Developers
Classifier: License :: OSI Approved :: MIT License
Classifier: Operating System :: OS Independent
Classifier: Programming Language :: Python :: 3
Classifier: Programming Language :: Python :: 3.8
Classifier: Programming Language :: Python :: 3.9
Classifier: Programming Language :: Python :: 3.10
Classifier: Programming Language :: Python :: 3.11
Classifier: Programming Language :: Python :: 3.12
Classifier: Programming Language :: Python :: 3.13
Classifier: Topic :: Internet :: WWW/HTTP :: Dynamic Content
Classifier: Topic :: Software Development :: Libraries :: Python Modules
Classifier: Topic :: System :: Distributed Computing
Requires-Python: >=3.8
License-File: LICENSE
Requires-Dist: requests>=2.25.0
Provides-Extra: dev
Requires-Dist: pytest>=6.0; extra == "dev"
Requires-Dist: pytest-cov; extra == "dev"
Requires-Dist: black; extra == "dev"
Requires-Dist: isort; extra == "dev"
Requires-Dist: flake8; extra == "dev"
Requires-Dist: mypy; extra == "dev"
Requires-Dist: tox; extra == "dev"
Requires-Dist: pre-commit; extra == "dev"
Provides-Extra: docs
Requires-Dist: sphinx; extra == "docs"
Requires-Dist: sphinx-rtd-theme; extra == "docs"
Dynamic: license-file
